{
    "Id": 0,
    "Location": [
      {
        "MapName": "itemB_room",
        "Position": [
          1,
          1
        ]
      },
      {
        "MapName": "itemB_room_broken",
        "Position": [
          1,
          1
        ]
      }
    ],
    "EventName": "GetItem Key | TileModify itemB_room StylesFront 1,1 #",
    "TriggerType": 1,
    "FlagCondition": {
      "Flag": [
        [
            "Key",
            false
        ]
      ],
      "NextFlag": [
        [
            "Key",
            true
        ]
      ]
    }
  }