{
  "Id": 2,
  "Location": [
    {
      "MapName": "reference_room",
      "Position": [
        8,
        19
      ]
    }
  ],
  "EventName": "Conversation Main7",
  "TriggerType": 0,
  "FlagCondition": {
    "Flag": [
      [
        "Progress5",
        true
      ],
      [
        "Progress6",
        false
      ],
      [
        "Azami_Peace",
        true
      ]
    ],
    "NextFlag": [
      [
        "Progress4",
        false
      ],
      [
        "Progress5",
        false
      ],
      [
        "Progress6",
        true
      ]
    ]
  }
}